{
  "id": "marienburgers",
  "nom": "Marienburgers (1a)",
  "grade": "1a",
  "source": "BSData",
  "regles_speciales": [
    {
      "nom": "Great Traders",
      "texte": "As natural traders with contacts in the merchant guilds Marienburg warbands receive a +1 bonus when attempting to find rare items.\nTo reflect their enormous wealth Marienburgers start off with an extra 100 gold crowns (600 in total) when fighting in a campaign.\nIn a one-off game they are permitted an extra 20% gold crowns when recruiting a warband.\nFor example, in a 1,000 gold crown game a Marienburger warband will have 1,200gc."
    }
  ],
  "profils": [
    {
      "id": "champion",
      "nom": "Champion",
      "type": "heros",
      "unique": false,
      "max": 2,
      "cout": 35,
      "stats": {
        "M": 4,
        "CC": 4,
        "CT": 3,
        "F": 3,
        "E": 3,
        "PV": 1,
        "I": 3,
        "A": 1,
        "Cd": 7
      },
      "acces_competences": [
        "academique",
        "combat",
        "equitation",
        "force",
        "tir",
        "vitesse"
      ]
    },
    {
      "id": "marksmen",
      "nom": "Marksmen",
      "type": "homme_de_main",
      "cout": 25,
      "stats": {
        "M": 4,
        "CC": 3,
        "CT": 3,
        "F": 3,
        "E": 3,
        "PV": 1,
        "I": 3,
        "A": 1,
        "Cd": 7
      },
      "acces_competences": [],
      "acces_competences_a_verifier": true
    },
    {
      "id": "mercenary_captain",
      "nom": "Mercenary Captain",
      "type": "heros",
      "unique": true,
      "max": 1,
      "cout": 60,
      "stats": {
        "M": 4,
        "CC": 4,
        "CT": 4,
        "F": 3,
        "E": 3,
        "PV": 1,
        "I": 4,
        "A": 1,
        "Cd": 8
      },
      "acces_competences": [
        "academique",
        "combat",
        "equitation",
        "force",
        "tir",
        "vitesse"
      ],
      "est_leader": true
    },
    {
      "id": "swordsmen",
      "nom": "Swordsmen",
      "type": "homme_de_main",
      "cout": 35,
      "stats": {
        "M": 4,
        "CC": 4,
        "CT": 3,
        "F": 3,
        "E": 3,
        "PV": 1,
        "I": 3,
        "A": 1,
        "Cd": 7
      },
      "acces_competences": [],
      "acces_competences_a_verifier": true
    },
    {
      "id": "warriors",
      "nom": "Warriors",
      "type": "homme_de_main",
      "cout": 25,
      "stats": {
        "M": 4,
        "CC": 3,
        "CT": 3,
        "F": 3,
        "E": 3,
        "PV": 1,
        "I": 3,
        "A": 1,
        "Cd": 7
      },
      "acces_competences": [],
      "acces_competences_a_verifier": true
    },
    {
      "id": "youngblood",
      "nom": "Youngblood",
      "type": "heros",
      "unique": false,
      "max": 2,
      "cout": 15,
      "stats": {
        "M": 4,
        "CC": 2,
        "CT": 2,
        "F": 3,
        "E": 3,
        "PV": 1,
        "I": 3,
        "A": 1,
        "Cd": 6
      },
      "acces_competences": [
        "academique",
        "combat",
        "equitation",
        "force",
        "tir",
        "vitesse"
      ]
    }
  ],
  "competences_speciales": []
}
